{
    "8.5": {
        "active": true,
        "release": {
            "type": "beta",
            "number": 2,
            "sha256_bz2": "91cd8664072d5fe61313db88cf855ebd576942c462a2e8097dabcbcc7561e1dc",
            "sha256_gz": "237833015ab63d5441fb781bc9848ae9bac4a7c3bdb1b6157139c41c1ea98b44",
            "sha256_xz": "02d0e9cbe8a1a022c2756c73c693f57b9c47b24545b1e82b72c7f7ffc3079193",
            "date": "28 Aug 2025",
            "baseurl": "https:\/\/downloads.php.net\/~daniels\/",
            "version": "8.5.0beta2",
            "files": {
                "bz2": {
                    "sha256": "91cd8664072d5fe61313db88cf855ebd576942c462a2e8097dabcbcc7561e1dc",
                    "path": "https:\/\/downloads.php.net\/~daniels\/php-8.5.0beta2.tar.bz2"
                },
                "gz": {
                    "sha256": "237833015ab63d5441fb781bc9848ae9bac4a7c3bdb1b6157139c41c1ea98b44",
                    "path": "https:\/\/downloads.php.net\/~daniels\/php-8.5.0beta2.tar.gz"
                },
                "xz": {
                    "sha256": "02d0e9cbe8a1a022c2756c73c693f57b9c47b24545b1e82b72c7f7ffc3079193",
                    "path": "https:\/\/downloads.php.net\/~daniels\/php-8.5.0beta2.tar.xz"
                }
            }
        },
        "dev_version": "8.5.0-dev"
    }
}
